{
  "image": "1.jpg",
  "predicted": "KM0000WM0T00H0000000000000070000",
  "det_count": 32,
  "format": "xyxy",
  "coord_type": "normalized",
  "model_w": 256,
  "model_h": 160,
  "detections": [
    {
      "x1": 0,
      "y1": 53,
      "x2": 4,
      "y2": 94,
      "score": 0.027777843177318573,
      "char": "K",
      "cls": 20
    },
    {
      "x1": 3,
      "y1": 21,
      "x2": 17,
      "y2": 51,
      "score": 0.027777835726737976,
      "char": "M",
      "cls": 22
    },
    {
      "x1": 8,
      "y1": 42,
      "x2": 27,
      "y2": 72,
      "score": 0.02777777798473835,
      "char": "0",
      "cls": 0
    },
    {
      "x1": 15,
      "y1": 112,
      "x2": 34,
      "y2": 143,
      "score": 0.02777777798473835,
      "char": "0",
      "cls": 0
    },
    {
      "x1": 26,
      "y1": 112,
      "x2": 43,
      "y2": 144,
      "score": 0.02777777798473835,
      "char": "0",
      "cls": 0
    },
    {
      "x1": 33,
      "y1": 88,
      "x2": 49,
      "y2": 121,
      "score": 0.02777777798473835,
      "char": "0",
      "cls": 0
    },
    {
      "x1": 29,
      "y1": 7,
      "x2": 70,
      "y2": 97,
      "score": 0.027777813374996185,
      "char": "W",
      "cls": 32
    },
    {
      "x1": 40,
      "y1": 41,
      "x2": 77,
      "y2": 66,
      "score": 0.027778154239058495,
      "char": "M",
      "cls": 22
    },
    {
      "x1": 58,
      "y1": 57,
      "x2": 72,
      "y2": 92,
      "score": 0.02777777798473835,
      "char": "0",
      "cls": 0
    },
    {
      "x1": 69,
      "y1": 0,
      "x2": 80,
      "y2": 21,
      "score": 0.027777787297964096,
      "char": "T",
      "cls": 29
    },
    {
      "x1": 75,
      "y1": 51,
      "x2": 90,
      "y2": 82,
      "score": 0.02777777798473835,
      "char": "0",
      "cls": 0
    },
    {
      "x1": 83,
      "y1": 95,
      "x2": 98,
      "y2": 133,
      "score": 0.02777777798473835,
      "char": "0",
      "cls": 0
    },
    {
      "x1": 92,
      "y1": 10,
      "x2": 104,
      "y2": 43,
      "score": 0.0277777798473835,
      "char": "H",
      "cls": 17
    },
    {
      "x1": 100,
      "y1": 0,
      "x2": 113,
      "y2": 21,
      "score": 0.02777777798473835,
      "char": "0",
      "cls": 0
    },
    {
      "x1": 104,
      "y1": 9,
      "x2": 122,
      "y2": 41,
      "score": 0.02777777798473835,
      "char": "0",
      "cls": 0
    },
    {
      "x1": 115,
      "y1": 54,
      "x2": 130,
      "y2": 97,
      "score": 0.02777782268822193,
      "char": "0",
      "cls": 0
    },
    {
      "x1": 115,
      "y1": 15,
      "x2": 144,
      "y2": 65,
      "score": 0.02777777798473835,
      "char": "0",
      "cls": 0
    },
    {
      "x1": 127,
      "y1": 8,
      "x2": 147,
      "y2": 39,
      "score": 0.02777777798473835,
      "char": "0",
      "cls": 0
    },
    {
      "x1": 137,
      "y1": 4,
      "x2": 153,
      "y2": 79,
      "score": 0.02777777798473835,
      "char": "0",
      "cls": 0
    },
    {
      "x1": 147,
      "y1": 0,
      "x2": 159,
      "y2": 23,
      "score": 0.02777777798473835,
      "char": "0",
      "cls": 0
    },
    {
      "x1": 152,
      "y1": 97,
      "x2": 169,
      "y2": 135,
      "score": 0.02777777798473835,
      "char": "0",
      "cls": 0
    },
    {
      "x1": 161,
      "y1": 102,
      "x2": 176,
      "y2": 142,
      "score": 0.02777777798473835,
      "char": "0",
      "cls": 0
    },
    {
      "x1": 169,
      "y1": 102,
      "x2": 185,
      "y2": 142,
      "score": 0.02777777798473835,
      "char": "0",
      "cls": 0
    },
    {
      "x1": 176,
      "y1": 92,
      "x2": 192,
      "y2": 135,
      "score": 0.02777777798473835,
      "char": "0",
      "cls": 0
    },
    {
      "x1": 186,
      "y1": 92,
      "x2": 198,
      "y2": 135,
      "score": 0.02777777798473835,
      "char": "0",
      "cls": 0
    },
    {
      "x1": 195,
      "y1": 91,
      "x2": 206,
      "y2": 136,
      "score": 0.02777777798473835,
      "char": "0",
      "cls": 0
    },
    {
      "x1": 197,
      "y1": 82,
      "x2": 218,
      "y2": 118,
      "score": 0.02777777798473835,
      "char": "0",
      "cls": 0
    },
    {
      "x1": 207,
      "y1": 34,
      "x2": 221,
      "y2": 73,
      "score": 0.07202665507793427,
      "char": "7",
      "cls": 7
    },
    {
      "x1": 217,
      "y1": 91,
      "x2": 230,
      "y2": 135,
      "score": 0.02777777798473835,
      "char": "0",
      "cls": 0
    },
    {
      "x1": 215,
      "y1": 75,
      "x2": 248,
      "y2": 118,
      "score": 0.02777782268822193,
      "char": "0",
      "cls": 0
    },
    {
      "x1": 228,
      "y1": 129,
      "x2": 252,
      "y2": 147,
      "score": 0.02777777798473835,
      "char": "0",
      "cls": 0
    },
    {
      "x1": 242,
      "y1": 74,
      "x2": 252,
      "y2": 109,
      "score": 0.02777777798473835,
      "char": "0",
      "cls": 0
    }
  ]
}